dict_fancy_printer/__init__.py
dict_fancy_printer/fancy_printer.py
dict_fancy_printer/functions.py
dict_fancy_printer/tests/__init__.py
dict_fancy_printer/tests/test_fancy_printer.py
dict_fancy_printer/tests/test_functions.py
dict_fancy_printer-0.1.2.dist-info/LICENSE
dict_fancy_printer-0.1.2.dist-info/METADATA
dict_fancy_printer-0.1.2.dist-info/WHEEL
dict_fancy_printer-0.1.2.dist-info/RECORD
