Metadata-Version: 2.1
Name: dict-fancy-printer
Version: 0.1.2
Summary: A simple library used to print python dictionaries in a fancier and more understandable way
Home-page: https://github.com/matteogabburo/dict-fancy-printer
License: Apache-2.0
Keywords: dict,printer,formatting
Author: Matteo Gabburo
Author-email: matteogabburo@gmail.com
Requires-Python: >=3.8,<4.0
Classifier: License :: OSI Approved :: Apache Software License
Classifier: Operating System :: OS Independent
Classifier: Programming Language :: Python :: 3
Classifier: Programming Language :: Python :: 3.8
Classifier: Programming Language :: Python :: 3.9
Classifier: Programming Language :: Python :: 3.10
Classifier: Programming Language :: Python :: 3.11
Classifier: Programming Language :: Python :: 3.12
Requires-Dist: termcolor (>=2.2.0,<3.0.0)
Project-URL: Repository, https://github.com/matteogabburo/dict-fancy-printer
